apycula/GW1N-1.pickle
apycula/GW1N-4.pickle
apycula/GW1N-9.pickle
apycula/GW1N-9C.pickle
apycula/GW1NS-4.pickle
apycula/GW1NZ-1.pickle
apycula/GW2A-18.pickle
apycula/GW2A-18C.pickle
apycula/GW5A-25A.pickle
apycula/GW5AST-138C.pickle
apycula/__init__.py
apycula/attrids.py
apycula/bitmatrix.py
apycula/bslib.py
apycula/chipdb.py
apycula/codegen.py
apycula/dat19.py
apycula/find_sdram_pins.py
apycula/fuse_h4x.py
apycula/gowin_pack.py
apycula/gowin_pll.py
apycula/gowin_unpack.py
apycula/ini_h4x.py
apycula/pindef.py
apycula/tiled_fuzzer.py
apycula/tm_h4x.py
apycula/tracing.py
apycula/wirenames.py
apycula-0.29.dist-info/licenses/LICENSE
apycula-0.29.dist-info/METADATA
apycula-0.29.dist-info/WHEEL
apycula-0.29.dist-info/entry_points.txt
apycula-0.29.dist-info/top_level.txt
apycula-0.29.dist-info/RECORD
