Metadata-Version: 2.4
Name: Apycula
Version: 0.29
Summary: Open Source tools for Gowin FPGAs
Home-page: https://github.com/YosysHQ/apicula
Author: Pepijn de Vos
Author-email: pepijndevos@gmail.com
Classifier: Programming Language :: Python :: 3
Classifier: License :: OSI Approved :: MIT License
Classifier: Operating System :: OS Independent
Requires-Python: >=3.9
License-File: LICENSE
Requires-Dist: crc
Dynamic: author
Dynamic: author-email
Dynamic: classifier
Dynamic: description
Dynamic: description-content-type
Dynamic: home-page
Dynamic: license-file
Dynamic: requires-dist
Dynamic: requires-python
Dynamic: summary
